{
  "=== UNKNOWN WORDS ===": "=== UNKNOWN WORDS ===",
  "мне<fade_LAT><123_NUM><jf_LAT>десять": "мне<fade_LAT><123_NUM><jf_LAT>десять",
  "минмалста": "минмалста",
  "холдоильника": "холдоильника",
  "рассета": "рассета",
  "санэпидемвредном": "санэпидемвредном",
  "слете": "слете",
  "СПОЛЗЕ": "СПОЛЗЕ",
  "СТАРЫХ": "СТАРЫХ",
  "БОЛЬНЫХ": "БОЛЬНЫХ",
  "СЪЕЗДЕ": "СЪЕЗДЕ",
  "ДНЕВНИК": "ДНЕВНИК",
  "псевдозорро": "псевдозорро",
  "и<c_LAT>чезло": "и<c_LAT>чезло",
  "феромонь": "феромонь",
  "хогвардс": "хогвардс",
  "ухухуху": "ухухуху",
  "понадкусанный": "понадкусанный",
  "веснух": "веснух",
  "обосралас": "обосралас",
  "архипка": "архипка",
  "бошки": "бошки",
  "уйло": "уйло",
  "хрустить": "хрустить",
  "обсераца": "обсераца",
  "лимпопы": "лимпопы",
  "княжней": "княжней",
  "клешнястый": "клешнястый",
  "барэ": "барэ",
  "ратару": "ратару",
  "друзями": "друзями",
  "джигурдиаду": "джигурдиаду",
  "отелль": "отелль",
  "нееет": "нееет",
  "деревян": "деревян",
  "оловянн": "оловянн",
  "алавяны": "алавяны",
  "плосткостью": "плосткостью",
  "ламанш": "ламанш",
  "чортичто": "чортичто",
  "щщастье": "щщастье",
  "ушел": "ушел",
  "обоссаные": "обоссаные",
  "монмартыр": "монмартыр",
  "бээээль": "бээээль",
  "выжигателем": "выжигателем",
  "горэнерго": "горэнерго",
  "ромбаба": "ромбаба",
  "бэдээсэму": "бэдээсэму",
  "негляж": "негляж",
  "валхвы": "валхвы",
  "пазорные": "пазорные",
  "ещщоб": "ещщоб",
  "чупокабра": "чупокабра",
  "муме": "муме",
  "сеппук": "сеппук",
  "мумы": "мумы",
  "зеон": "зеон",
  "фиу": "фиу",
  "скорэй": "скорэй",
  "несварэнье": "несварэнье",
  "оой": "оой",
  "вээээй": "вээээй",
  "гнездованья": "гнездованья",
  "комат": "комат",
  "пиздюк": "пиздюк",
  "партянки": "партянки",
  "владимыч": "владимыч",
  "изрек": "изрек",
  "кинулися": "кинулися",
  "нее": "нее",
  "щитаешь": "щитаешь",
  "ишшо": "ишшо",
  "кинотеатор": "кинотеатор",
  "принесет": "принесет",
  "кивнет": "кивнет",
  "застегнет": "застегнет",
  "массонских": "массонских",
  "чяте": "чяте",
  "высквозь": "высквозь",
  "вынзи": "вынзи",
  "акапелла": "акапелла",
  "гриммы": "гриммы",
  "перром": "перром",
  "номиниро": "номиниро",
  "зомбей": "зомбей",
  "стройну": "стройну",
  "ласкову": "ласкову",
  "красиву": "красиву",
  "бежин": "бежин",
  "ружжа": "ружжа",
  "ружа": "ружа",
  "сермяж": "сермяж",
  "запахнувшысь": "запахнувшысь",
  "потрясенный": "потрясенный",
  "откашлявшысь": "откашлявшысь",
  "помедле": "помедле",
  "ннее": "ннее",
  "неверьи": "неверьи",
  "ойвся": "ойвся",
  "суньцзы": "суньцзы",
  "повинну": "повинну",
  "неповинну": "неповинну",
  "альбиночка": "альбиночка",
  "пририфмовали": "пририфмовали",
  "ритым": "ритым",
  "какойта": "какойта",
  "дуракт": "дуракт",
  "терран": "терран",
  "влаки": "влаки",
  "мертваго": "мертваго",
  "роллингов": "роллингов",
  "мышцев": "мышцев",
  "шырот": "шырот",
  "утрехтского": "утрехтского",
  "ардер": "ардер",
  "октябрятов": "октябрятов",
  "рэю": "рэю",
  "няшность": "няшность",
  "мусье": "мусье",
  "конгратулейсан": "конгратулейсан",
  "оцень": "оцень",
  "хоросо": "хоросо",
  "павлиасвили": "павлиасвили",
  "покуша": "покуша",
  "вомбатюшка": "вомбатюшка",
  "щелкал": "щелкал",
  "рейхсталин": "рейхсталин",
  "недержаньем": "недержаньем",
  "оплодотварила": "оплодотварила",
  "эрэнкакнул": "эрэнкакнул",
  "демоничес": "демоничес",
  "шикитано": "шикитано",
  "жики": "жики",
  "мимимимические": "мимимимические",
  "мацуо": "мацуо",
  "маслятовцев": "маслятовцев",
  "груздин": "груздин",
  "приподъездных": "приподъездных",
  "тарэлькой": "тарэлькой",
  "падзорный": "падзорный",
  "сумкин": "сумкин",
  "перекатываецца": "перекатываецца",
  "сувай": "сувай",
  "хитрий": "хитрий",
  "який": "який",
  "тааак": "тааак",
  "таплан": "таплан",
  "изю": "изю",
  "укулельники": "укулельники",
  "укулель": "укулель",
  "пропечаталася": "пропечаталася",
  "невинноватый": "невинноватый",
  "мося": "мося",
  "невоо": "невоо",
  "ружон": "ружон",
  "подпледном": "подпледном",
  "врифмую": "врифмую",
  "ноосферические": "ноосферические",
  "франкенштейна": "франкенштейна",
  "сшываю": "сшываю",
  "едаааааа": "едаааааа",
  "аньолотофобией": "аньолотофобией",
  "взамуж": "взамуж",
  "венерианин": "венерианин",
  "пудак": "пудак",
  "одиноковом": "одиноковом",
  "эксель": "эксель",
  "бэгэ": "бэгэ",
  "ашшурбанипала": "ашшурбанипала",
  "колибрикрушенья": "колибрикрушенья",
  "тибул": "тибул",
  "мумитролль": "мумитролль",
  "туу": "туу",
  "понавыкидывали": "понавыкидывали",
  "пацанчик-хипстер": "пацанчик-хипстер",
  "осетринити": "осетринити",
  "гони-ка": "гони-ка",
  "томир": "томир",
  "альфаплане": "альфаплане",
  "гиппофилом": "гиппофилом",
  "рамоном": "рамоном",
  "скоммунизженные": "скоммунизженные",
  "наикрутейшая": "наикрутейшая",
  "татуха": "татуха",
  "кавайных": "кавайных",
  "австра": "австра",
  "препинательных": "препинательных",
  "бровьми": "бровьми",
  "отщот": "отщот",
  "жызнерадостное": "жызнерадостное",
  "прожыта": "прожыта",
  "навывает": "навывает",
  "собаку»": "собаку»",
  "бандурин": "бандурин",
  "плазмган": "плазмган",
  "поплелся": "поплелся",
  "четверо,": "четверо,",
  "как-то:": "как-то:",
  "жан-пьер": "жан-пьер",
  "эдемовском": "эдемовском",
  "чиполино": "чиполино",
  "бэлле": "бэлле",
  "сантаклаус": "сантаклаус",
  "обитайет": "обитайет",
  "сдорофьенный": "сдорофьенный",
  "стотыщ": "стотыщ",
  "рассек": "рассек",
  "экспромтъ": "экспромтъ",
  "<n_LAT>еред": "<n_LAT>еред",
  "тараканоморфного": "тараканоморфного",
  "печоный": "печоный",
  "мокроштанный": "мокроштанный",
  "поюзать": "поюзать",
  "подрацца": "подрацца",
  "побухать": "побухать",
  "гетеро": "гетеро",
  "вырко": "вырко",
  "яраженный": "яраженный",
  "рывают": "рывают",
  "ямбичес": "ямбичес",
  "ненаточенные": "ненаточенные",
  "тивилизоре": "тивилизоре",
  "мегасуперстар": "мегасуперстар",
  "щечки": "щечки",
  "татив": "татив",
  "сползе": "сползе",
  "нановирус": "нановирус",
  "мэрзких": "мэрзких",
  "умэр": "умэр",
  "поражонный": "поражонный",
  "исусь": "исусь",
  "неможечко": "неможечко",
  "пур-ква": "пур-ква",
  "диэти": "диэти",
  "ламид": "ламид",
  "деськопеек": "деськопеек",
  "ебуч": "ебуч",
  "песде????!!!": "песде????!!!",
  "сиводнэ": "сиводнэ",
  "чупакабро": "чупакабро",
  "добрэй": "добрэй",
  "забыли!": "забыли!",
  "<6_NUM>-ую": "<6_NUM>-ую",
  "кое-как!": "кое-как!",
  "ХУЯК!!!\"": "ХУЯК!!!\"",
  "рядовая": "рядовая",
  "цикнув": "цикнув",
  "побарабану": "побарабану",
  "ебязь": "ебязь",
  "сюдзин": "сюдзин",
  "накато": "накато",
  "такамада": "такамада",
  "БУНТАРЬ": "БУНТАРЬ",
  "НОВАТОР": "НОВАТОР",
  "ВСЕМУ": "ВСЕМУ",
  "ВИНОЙ": "ВИНОЙ",
  "ПРОКЛЯТЫЙ": "ПРОКЛЯТЫЙ",
  "ПРОШУ": "ПРОШУ",
  "ПРОЩЕНИЯ": "ПРОЩЕНИЯ",
  "РЕБЯТА": "РЕБЯТА",
  "портфэля": "портфэля",
  "та-да-да-да": "та-да-да-да",
  "рапунциль": "рапунциль",
  "тащщи": "тащщи",
  "чатиках": "чатиках",
  "урлы": "урлы",
  "исуско": "исуско",
  "яйцерезку": "яйцерезку",
  "растроен": "растроен",
  "хихик-с": "хихик-с",
  "мусчина": "мусчина",
  "ходють": "ходють",
  "стафайтесь": "стафайтесь",
  "биттэ": "биттэ",
  "идет": "идет",
  "барналея": "барналея",
  "тираннозавыр": "тираннозавыр",
  "теплоль": "теплоль",
  "воооот": "воооот",
  "барикады": "барикады",
  "хлопочь": "хлопочь",
  "заключонный": "заключонный",
  "вагинск": "вагинск",
  "влено": "влено",
  "очок": "очок",
  "вульгарн": "вульгарн",
  "карабасхан": "карабасхан",
  "буратинбека": "буратинбека",
  "буратинбек": "буратинбек",
  "войдем": "войдем",
  "брамстеньг": "брамстеньг",
  "бомбрамстеньг": "бомбрамстеньг",
  "ремен": "ремен",
  "упса": "упса",
  "поувольнялась": "поувольнялась",
  "травесть": "травесть",
  "вышытом": "вышытом",
  "сарацына": "сарацына",
  "спешыл": "спешыл",
  "бубубу": "бубубу",
  "бубу": "бубу",
  "етит": "етит",
  "куклуксклановский": "куклуксклановский",
  "калпак": "калпак",
  "спрягол": "спрягол",
  "простяся": "простяся",
  "немного,": "немного,",
  "олигофрен,": "олигофрен,",
  "немного»": "немного»",
  "Рефрен.": "Рефрен.",
  "учон": "учон",
  "начвытрезвителя": "начвытрезвителя",
  "ешивах": "ешивах",
  "моглы": "моглы",
  "платову": "платову",
  "зависи": "зависи",
  "хотю": "хотю",
  "ланнистеры": "ланнистеры",
  "гигантоман": "гигантоман",
  "тарел": "тарел",
  "жывшых": "жывшых",
  "подсдам": "подсдам",
  "полужыдок": "полужыдок",
  "жыдовской": "жыдовской",
  "пофлотск": "пофлотск",
  "лавреньтевских": "лавреньтевских",
  "тадэуш": "тадэуш",
  "риот": "риот",
  "фтридэ": "фтридэ",
  "гестапа": "гестапа",
  "бикицер": "бикицер",
  "соглядают": "соглядают",
  "ковбойцев": "ковбойцев",
  "тададада": "тададада",
  "рэцепту": "рэцепту",
  "рибы": "рибы",
  "еврэйски": "еврэйски",
  "бером": "бером",
  "пового": "пового",
  "запыхавшысь": "запыхавшысь",
  "отдаки": "отдаки",
  "вайся": "вайся",
  "цэнтнер": "цэнтнер",
  "неопера": "неопера",
  "подвиньсь": "подвиньсь",
  "любезн": "любезн",
  "реабили": "реабили",
  "тасьон": "тасьон",
  "какашк": "какашк",
  "аркашк": "аркашк",
  "ливси": "ливси",
  "адэль": "адэль",
  "крепостниче": "крепостниче",
  "архидемон": "архидемон",
  "боска": "боска",
  "бардзо": "бардзо",
  "карагандинкой": "карагандинкой",
  "анду": "анду",
  "додэ": "додэ",
  "дода": "дода",
  "верды": "верды",
  "хотей": "хотей",
  "блюрэе": "блюрэе",
  "бубли": "бубли",
  "фехтовальщической": "фехтовальщической",
  "доуэль": "доуэль",
  "систей": "систей",
  "пледнолицый": "пледнолицый",
  "приежжайте": "приежжайте",
  "гогену": "гогену",
  "хельсинга": "хельсинга",
  "соо": "соо",
  "бражу": "бражу",
  "опен": "опен",
  "винворд": "винворд",
  "человеко": "человеко",
  "деградиро": "деградиро",
  "вайте": "вайте",
  "зодавили": "зодавили",
  "орфагрофический": "орфагрофический",
  "прочтем": "прочтем",
  "поржем": "поржем",
  "спасет": "спасет",
  "декват": "декват",
  "подождешь": "подождешь",
  "картош": "картош",
  "архипке": "архипке",
  "начнем": "начнем",
  "вздернув": "вздернув",
  "обсценн": "обсценн",
  "дроня": "дроня",
  "ганешу": "ганешу",
  "безсексье": "безсексье",
  "системати": "системати",
  "ничков": "ничков",
  "несет": "несет",
  "шепчеш": "шепчеш",
  "фтыкаеш": "фтыкаеш",
  "безынтернетное": "безынтернетное",
  "томуж": "томуж",
  "скуко": "скуко",
  "хуйма": "хуйма",
  "ученые": "ученые",
  "зеленые": "зеленые",
  "трехлапый": "трехлапый",
  "чупакабры": "чупакабры",
  "шахиджаняну": "шахиджаняну",
  "балгоадрить": "балгоадрить",
  "охчу": "охчу",
  "слеопечтаатю": "слеопечтаатю",
  "ыбстро": "ыбстро",
  "оу": "оу",
  "воспаленная": "воспаленная",
  "чере": "чере",
  "интимн": "интимн",
  "волося": "волося",
  "ползет": "ползет",
  "темном": "темном",
  "покоренной": "покоренной",
  "теплых": "теплых",
  "чился": "чился",
  "мудень": "мудень",
  "нифниф": "нифниф",
  "вопщето": "вопщето",
  "нуфнуф": "нуфнуф",
  "япона": "япона",
  "уи": "уи",
  "акела": "акела",
  "баскервиль": "баскервиль",
  "одне": "одне",
  "поймешь": "поймешь",
  "мудил": "мудил",
  "откадил": "откадил",
  "чере<c_LAT>чур": "чере<c_LAT>чур",
  "лезуб": "лезуб",
  "шщупалца": "шщупалца",
  "супкультуре": "супкультуре",
  "смахнет": "смахнет",
  "вздохнет": "вздохнет",
  "запоет": "запоет",
  "экто": "экто",
  "право...": "право...",
  "никому...": "никому...",
  "блещщут": "блещщут",
  "тентакль": "тентакль",
  "цыклоп": "цыклоп",
  "невоскресших": "невоскресших",
  "беримор": "беримор",
  "замерзших": "замерзших",
  "растет": "растет",
  "пооживляли": "пооживляли",
  "внутре": "внутре",
  "легок": "легок",
  "легким": "легким",
  "троеточие": "троеточие",
  "рас<c_LAT>трелять": "рас<c_LAT>трелять",
  "мертвой": "мертвой",
  "Знакомьтесь.": "Знакомьтесь.",
  "Это": "Это",
  "Саша": "Саша",
  "Моцарт.": "Моцарт.",
  "Поэт.": "Поэт.",
  "Немножко": "Немножко",
  "музыкант.": "музыкант.",
  "Дантес": "Дантес",
  "Сольери!": "Сольери!",
  "Мутант.": "Мутант.",
  "верест": "верест",
  "порутчик": "порутчик",
  "елке": "елке",
  "доверели": "доверели",
  "ИдУвДоЛьДлИнНоГоЗаБоРа": "ИдУвДоЛьДлИнНоГоЗаБоРа",
  "ВгРаФфИтИнЕпОнЯтНыХсЛоВ": "ВгРаФфИтИнЕпОнЯтНыХсЛоВ",
  "ИрАдУюСьУвИдЕвНаДпИсЬ": "ИрАдУюСьУвИдЕвНаДпИсЬ",
  "неношенное": "неношенное",
  "целллюлит": "целллюлит",
  "вмерзло": "вмерзло",
  "ницшев": "ницшев",
  "фроммов": "фроммов",
  "стоцкую": "стоцкую",
  "ускоренье": "ускоренье",
  "прыщщик": "прыщщик",
  "ОнО": "ОнО",
  "ризонт": "ризонт",
  "удушенья": "удушенья",
  "утопленья": "утопленья",
  "телепатируя": "телепатируя",
  "расстаю": "расстаю",
  "пробелвдругпересталработать": "пробелвдругпересталработать",
  "хотьславабогучтоестьввод": "хотьславабогучтоестьввод",
  "неразврат": "неразврат",
  "пентакль": "пентакль",
  "васссссся": "васссссся",
  "щедевыр": "щедевыр",
  "бодяж": "бодяж",
  "лелейка": "лелейка",
  "рассосуцца": "рассосуцца",
  "чевож": "чевож",
  "перпетум": "перпетум",
  "массаракш": "массаракш",
  "схуяль": "схуяль",
  "гордицца": "гордицца",
  "обнимацца": "обнимацца",
  "цыловацца": "цыловацца",
  "реинкарнировавшись": "реинкарнировавшись",
  "жывому": "жывому",
  "сотрем": "сотрем",
  "тещи": "тещи",
  "шизомуза": "шизомуза",
  "гондольерша": "гондольерша",
  "бордельеро": "бордельеро",
  "упреком": "упреком",
  "держуся": "держуся",
  "хлебсолью": "хлебсолью",
  "дирижаблих": "дирижаблих",
  "микрорадугой": "микрорадугой",
  "прелюбдеяниях": "прелюбдеяниях",
  "пушыста": "пушыста",
  "крыжопыль": "крыжопыль",
  "марсиансих": "марсиансих",
  "несется": "несется",
  "креветы": "креветы",
  "наночлена": "наночлена",
  "франкенштейн": "франкенштейн",
  "додека": "додека",
  "эдров": "эдров",
  "йося": "йося",
  "конфигураци": "конфигураци",
  "ложииись!": "ложииись!",
  "Маресьев": "Маресьев",
  "тепло,": "тепло,",
  "еда!": "еда!",
  "доспехах:": "доспехах:",
  "\"Куда?\"": "\"Куда?\"",
  "суфлеру": "суфлеру",
  "хозе": "хозе",
  "заля": "заля",
  "хотите?": "хотите?",
  "наклат": "наклат",
  "бобрам-с": "бобрам-с",
  "самку,": "самку,",
  "самец,": "самец,",
  "называться?": "называться?",
  "Свинец!": "Свинец!",
  "искра?": "искра?",
  "испра": "испра",
  "небы": "небы",
  "тием": "тием",
  "амбидекстра": "амбидекстра",
  "убедиться?": "убедиться?",
  "никаноры": "никаноры",
  "маршеле": "маршеле",
  "прошледовать": "прошледовать",
  "куштам": "куштам",
  "леонардов": "леонардов",
  "коктов": "коктов",
  "заслужыть": "заслужыть",
  "совершыл": "совершыл",
  "деляфер": "деляфер",
  "киловатсон": "киловатсон",
  "килобаксов": "килобаксов",
  "загро": "загро",
  "мождать": "мождать",
  "ушераздираю": "ушераздираю",
  "щее": "щее",
  "обрящ": "обрящ",
  "дыряву": "дыряву",
  "высокохудоже": "высокохудоже",
  "ственность": "ственность",
  "плывет": "плывет",
  "дракониха": "дракониха",
  "гатив": "гатив",
  "гомогог": "гомогог",
  "БАрбара": "БАрбара",
  "БРЫльська": "БРЫльська",
  "вдохновенн": "вдохновенн",
  "говейн": "говейн",
  "кирюха": "кирюха",
  "прихорашиватель": "прихорашиватель",
  "увеличенье": "увеличенье",
  "меней": "меней",
  "бабульк": "бабульк",
  "сычуанем": "сычуанем",
  "гурцзы": "гурцзы",
  "пришвины": "пришвины",
  "ланфреном": "ланфреном",
  "ланфром": "ланфром",
  "кабрат": "кабрат",
  "сурраунд": "сурраунд",
  "вениамины": "вениамины",
  "друзем": "друзем",
  "антидрузь": "антидрузь",
  "дизерт": "дизерт",
  "иглов": "иглов",
  "прелюбодеяньем": "прелюбодеяньем",
  "назовем": "назовем",
  "секыс": "секыс",
  "щелкнуло": "щелкнуло",
  "полцарств": "полцарств",
  "модан": "модан",
  "анджолна": "анджолна",
  "лишень": "лишень",
  "покусають": "покусають",
  "фасо": "фасо",
  "султаймс": "султаймс",
  "легкоусваиваемого": "легкоусваиваемого",
  "ститут": "ститут",
  "бензо": "бензо",
  "лавист": "лавист",
  "полож": "полож",
  "ронин": "ронин",
  "дзюдом": "дзюдом",
  "моголова": "моголова",
  "хухра": "хухра",
  "мухра": "мухра",
  "варпа": "варпа",
  "космокрейсер": "космокрейсер",
  "огра": "огра",
  "вислопузых": "вислопузых",
  "кандал": "кандал",
  "режил": "режил",
  "лесбийством": "лесбийством",
  "кунгфу": "кунгфу",
  "чебуран": "чебуран",
  "па<ŏ_LAT>ло": "па<ŏ_LAT>ло",
  "эпи": "эпи",
  "бонгов": "бонгов",
  "хаваньи": "хаваньи",
  "пиплом": "пиплом",
  "пикасс": "пикасс",
  "пиписк": "пиписк",
  "жылу": "жылу",
  "отоща": "отоща",
  "висенье": "висенье",
  "ефросенье": "ефросенье",
  "тудыть": "тудыть",
  "етить": "етить",
  "эврисфея": "эврисфея",
  "прожжоным": "прожжоным",
  "поупотребляю": "поупотребляю",
  "простраствовременной": "простраствовременной",
  "снегуро": "снегуро",
  "интрамамморальный": "интрамамморальный",
  "отношаться": "отношаться",
  "купииите": "купииите",
  "представлялася": "представлялася",
  "прижымала": "прижымала",
  "отжывшых": "отжывшых",
  "бойлю": "бойлю",
  "открывшы": "открывшы",
  "вноздрил": "вноздрил",
  "либиду": "либиду",
  "либид": "либид",
  "хемингуэя": "хемингуэя",
  "моменто": "моменто",
  "варлаф": "варлаф",
  "фууу": "фууу",
  "ярик": "ярик",
  "ублаженья": "ублаженья",
  "тактиль": "тактиль",
  "такэминакаты": "такэминакаты",
  "отличьи": "отличьи",
  "моя?": "моя?",
  "чужая?": "чужая?",
  "патамушто": "патамушто",
  "морквой": "морквой",
  "няшных": "няшных",
  "сбэкапить": "сбэкапить",
  "трясет": "трясет",
  "стеклам": "стеклам",
  "дернув": "дернув",
  "землей": "землей",
  "недовинченного": "недовинченного",
  "мойшы": "мойшы",
  "гейшы": "гейшы",
  "побольш": "побольш",
  "пойдет": "пойдет",
  "прервется": "прервется",
  "йогиня": "йогиня",
  "педрила": "педрила",
  "зовется": "зовется",
  "отнють": "отнють",
  "педрилам": "педрилам",
  "добьемся": "добьемся",
  "средневековии": "средневековии",
  "придает": "придает",
  "титьми": "титьми",
  "предпочел": "предпочел",
  "многообразьем": "многообразьем",
  "эцилопп": "эцилопп",
  "чатланин": "чатланин",
  "пацак": "пацак",
  "камшот": "камшот",
  "келля": "келля",
  "телосложенье": "телосложенье",
  "упорхала": "упорхала",
  "нарушыли": "нарушыли",
  "капралью": "капралью",
  "приват": "приват",
  "минобыр": "минобыр",
  "гекыльберри": "гекыльберри",
  "полдуэта": "полдуэта",
  "возьмешь": "возьмешь",
  "пошивая": "пошивая",
  "бургомистыр": "бургомистыр",
  "какий": "какий",
  "витта": "витта",
  "зачеркнуто": "зачеркнуто",
  "дурдо": "дурдо",
  "гопа": "гопа",
  "нарвешься": "нарвешься",
  "прочту?": "прочту?",
  "веселая": "веселая",
  "завелся": "завелся",
  "имхой": "имхой",
  "тормашк": "тормашк",
  "гармонья": "гармонья",
  "иньянь": "иньянь",
  "синьпьянь": "синьпьянь",
  "сростаются": "сростаются",
  "растождествленный": "растождествленный",
  "фуэт": "фуэт",
  "несецца": "несецца",
  "недоодетых": "недоодетых",
  "материкаться": "материкаться",
  "сисяндр": "сисяндр",
  "поперхнувшысь": "поперхнувшысь",
  "абсорбентопивофило": "абсорбентопивофило",
  "манюсенький": "манюсенький",
  "пентограммой": "пентограммой",
  "слвоа": "слвоа",
  "смеашлись": "смеашлись",
  "бумгае": "бумгае",
  "хтоя": "хтоя",
  "разорбать": "разорбать",
  "улвалиавет": "улвалиавет",
  "блеать": "блеать",
  "кунжут?": "кунжут?",
  "люминисцировал": "люминисцировал",
  "милисекунды": "милисекунды",
  "растленье": "растленье",
  "муммитролль": "муммитролль",
  "висель": "висель",
  "эври": "эври",
  "хатсон": "хатсон",
  "гено": "гено",
  "прожыл": "прожыл",
  "\"говно\"": "\"говно\"",
  "дантэса": "дантэса",
  "кипить": "кипить",
  "ошыбся": "ошыбся",
  "снежынках": "снежынках",
  "поглажывая": "поглажывая",
  "лизбе": "лизбе",
  "мертвая": "мертвая",
  "ребя": "ребя",
  "конвульсируешь": "конвульсируешь",
  "лосов": "лосов",
  "екнуло": "екнуло",
  "сказал:": "сказал:",
  "пойдемте": "пойдемте",
  "мОзги": "мОзги",
  "ЗАЧЕМ": "ЗАЧЕМ",
  "восприятьем": "восприятьем",
  "пугаЧТОва": "пугаЧТОва",
  "ништяяяк": "ништяяяк",
  "лодцом": "лодцом",
  "ствовать": "ствовать",
  "капчу": "капчу",
  "корнелюку": "корнелюку",
  "трабас": "трабас",
  "чморя": "чморя",
  "бывалыча": "бывалыча",
  "кришен": "кришен",
  "корпускулярноволновой": "корпускулярноволновой",
  "истанбула": "истанбула",
  "поват": "поват",
  "ноблесс": "ноблесс",
  "мороженку": "мороженку",
  "оближь": "оближь",
  "нищасный": "нищасный",
  "жио": "жио",
  "крепчааааай": "крепчааааай",
  "идешь": "идешь",
  "мандры": "мандры",
  "тия": "тия",
  "неевклид": "неевклид",
  "остыт": "остыт",
  "робяты": "робяты",
  "проплывет": "проплывет",
  "ямалонененецкий": "ямалонененецкий",
  "стеченьем": "стеченьем",
  "мума": "мума",
  "сойдет": "сойдет",
  "тибальт": "тибальт",
  "руши": "руши",
  "встаем": "встаем",
  "товься": "товься",
  "поверхностноактивен": "поверхностноактивен",
  "йее": "йее",
  "обаялся": "обаялся",
  "падлюки": "падлюки",
  "аллейкум": "аллейкум",
  "игореша": "игореша",
  "приемного": "приемного",
  "огнем": "огнем",
  "смущенно": "смущенно",
  "кладет": "кладет",
  "доползет": "доползет",
  "корыыыы": "корыыыы",
  "щелочку": "щелочку",
  "але": "але",
  "найдется": "найдется",
  "сплетенных": "сплетенных",
  "<c_LAT>вистни": "<c_LAT>вистни",
  "трясус": "трясус",
  "бодиарта": "бодиарта",
  "однопла": "однопла",
  "нетян": "нетян",
  "кейтаро": "кейтаро",
  "дзюды": "дзюды",
  "овней": "овней",
  "облапав": "облапав",
  "годицц": "годицц",
  "согрелося": "согрелося",
  "\"ежи": "\"ежи",
  "кустом\"": "кустом\"",
  "несуществу": "несуществу",
  "расстерялся": "расстерялся",
  "вошел": "вошел",
  "гладиатррр": "гладиатррр",
  "юлбюл": "юлбюл",
  "ябет": "ябет",
  "суицыдальный": "суицыдальный",
  "кастров": "кастров",
  "развеж": "развеж",
  "перфекци": "перфекци",
  "онист": "онист",
  "кэцэ": "кэцэ",
  "сямисен": "сямисен",
  "мени": "мени",
  "искусс": "искусс",
  "интиллегенту": "интиллегенту",
  "письки!": "письки!",
  "одна!": "одна!",
  "романсы,": "романсы,",
  "Засуньте": "Засуньте",
  "Подальше": "Подальше",
  "греха,": "греха,",
  "Зухра": "Зухра",
  "Пора": "Пора",
  "Приделал": "Приделал",
  "Фуко": "Фуко",
  "кукушка:": "кукушка:",
  "\"Куко!\"": "\"Куко!\"",
  "\"Подлец!\"": "\"Подлец!\"",
  "\"Фашист!\",": "\"Фашист!\",",
  "\"Убийца!\",": "\"Убийца!\",",
  "подам!\"": "подам!\"",
  "Однако,": "Однако,",
  "Та-дам!": "Та-дам!",
  "мазо-садо": "мазо-садо",
  "наемных": "наемных",
  "Кроты": "Кроты",
  "Супермену": "Супермену",
  "июль?": "июль?",
  "февраль?": "февраль?",
  "тимофеич": "тимофеич",
  "рейхенбахских": "рейхенбахских",
  "постойте,": "постойте,",
  "она?": "она?",
  "черный-черный": "черный-черный",
  "черном": "черном",
  "сверк-сверк!": "сверк-сверк!",
  "октопод": "октопод",
  "треугольность": "треугольность",
  "сантиметро": "сантиметро",
  "чайку?": "чайку?",
  "(или": "(или",
  "локтя)": "локтя)",
  "сиам": "сиам",
  "ученым": "ученым",
  "коню?": "коню?",
  "похлава": "похлава",
  "ехо": "ехо",
  "дьюара": "дьюара",
  "годник": "годник",
  "стотридцатый": "стотридцатый",
  "казил": "казил",
  "недокрашена": "недокрашена",
  "прокра": "прокра",
  "дроздофф": "дроздофф",
  "прокладк": "прокладк",
  "плююс": "плююс",
  "мясопотамии": "мясопотамии",
  "мясопотамов": "мясопотамов",
  "попробуй-ка": "попробуй-ка",
  "зачинать-то": "зачинать-то",
  "изнасила": "изнасила",
  "кончилась,": "кончилась,",
  "годности.": "годности.",
  "можем.": "можем.",
  "криобани": "криобани",
  "диндон": "диндон",
  "узбекистоны": "узбекистоны",
  "Ваши": "Ваши",
  "указъ": "указъ",
  "отнын": "отнын",
  "сепукой": "сепукой",
  "дзенит": "дзенит",
  "пледовитом": "пледовитом",
  "цептив": "цептив",
  "полуприоткрывши": "полуприоткрывши",
  "осмотыр": "осмотыр",
  "запитал": "запитал",
  "причоску": "причоску",
  "заброшенно": "заброшенно",
  "моментой": "моментой",
  "покружыв": "покружыв",
  "изкуств": "изкуств",
  "премног": "премног",
  "плейбей": "плейбей",
  "игломан": "игломан",
  "иглородных": "иглородных",
  "горЛаниЛи": "горЛаниЛи",
  "сЦенЫ": "сЦенЫ",
  "вЛИяНЬем": "вЛИяНЬем",
  "ДЕцИБеЛ": "ДЕцИБеЛ",
  "сТИШок": "сТИШок",
  "пОБУлЬКав": "пОБУлЬКав",
  "пОПЕНяСЬ": "пОПЕНяСЬ",
  "ВСКИПЕЛ": "ВСКИПЕЛ",
  "шицу": "шицу",
  "вая": "вая",
  "сипеда": "сипеда",
  "постишь": "постишь",
  "бронштейны": "бронштейны",
  "кацы": "кацы",
  "уборщи": "уборщи",
  "«ответ»": "«ответ»",
  "«впишите": "«впишите",
  "ответ»": "ответ»",
  "додрях": "додрях",
  "алко": "алко",
  "трудо": "трудо",
  "шопо": "шопо",
  "голизм": "голизм",
  "(привстал": "(привстал",
  "офицер)": "офицер)",
  "топлюс": "топлюс",
  "тосковед": "тосковед",
  "отскрипело": "отскрипело",
  "постскрип": "постскрип",
  "батлы": "батлы",
  "ебатл": "ебатл",
  "замог": "замог",
  "халоу": "халоу",
  "денев": "денев",
  "опиз": "опиз",
  "рии": "рии",
  "милота": "милота",
  "контральт": "контральт",
  "везешь": "везешь",
  "сфокусиро": "сфокусиро",
  "вацца": "вацца",
  "сийся": "сийся",
  "снобит": "снобит",
  "падам": "падам",
  "впадам": "впадам",
  "рожоны": "рожоны",
  "рожонов": "рожонов",
  "духаст": "духаст",
  "ухаст": "ухаст",
  "удро": "удро",
  "гаврюша": "гаврюша",
  "вобшэ": "вобшэ",
  "тортилле": "тортилле",
  "подвеск": "подвеск",
  "шыроком": "шыроком",
  "юуннемерв": "юуннемерв",
  "унышам": "унышам",
  "камментом": "камментом",
  "пешите": "пешите",
  "прэнэбрэгитэ": "прэнэбрэгитэ",
  "эсок": "эсок",
  "христы": "христы",
  "тяжелом": "тяжелом",
  "наночь": "наночь",
  "валгале": "валгале",
  "«Какого": "«Какого",
  "Ферзя": "Ферзя",
  "Слыхать?": "Слыхать?",
  "кафказ": "кафказ",
  "крышнам!": "крышнам!",
  "торреадору": "торреадору",
  "принцеса": "принцеса",
  "инвест": "инвест",
  "трехстопным": "трехстопным",
  "четырехстопным": "четырехстопным",
  "акбарней": "акбарней",
  "теток": "теток",
  "бодун-бодун": "бодун-бодун",
  "тяв-тяв": "тяв-тяв",
  "атиллы": "атиллы",
  "тортила": "тортила",
  "хозэ": "хозэ",
  "киан": "киан",
  "гарим": "гарим",
  "эгегегейш": "эгегегейш",
  "олеолег": "олеолег",
  "трубогибным": "трубогибным",
  "трубогибщик": "трубогибщик",
  "курсовиков": "курсовиков",
  "новне": "новне",
  "заполненью": "заполненью",
  "полуусоп": "полуусоп",
  "стажор": "стажор",
  "прикласть": "прикласть",
  "(приложить?)": "(приложить?)",
  "резюму": "резюму",
  "ницу": "ницу",
  "чече": "чече",
  "санэпидеминспектор": "санэпидеминспектор",
  "катес": "катес",
  "вцарапай": "вцарапай",
  "нычем": "нычем",
  "угну": "угну",
  "виляючи": "виляючи",
  "трофоб": "трофоб",
  "МЕЛКИ": "МЕЛКИ",
  "эксгиб": "эксгиб",
  "боже!": "боже!",
  "лжелже": "лжелже",
  "соит": "соит",
  "штука*": "штука*",
  "(нижестоящих)": "(нижестоящих)",
  "перехдим": "перехдим",
  "закннсти": "закннсти",
  "уптребленья": "уптребленья",
  "яслунрев": "яслунрев",
  "ыниволоп": "ыниволоп",
  "ядйорп": "ядйорп",
  "слющяй": "слющяй",
  "хватэт": "хватэт",
  "ложноглазки": "ложноглазки",
  "ложносекса": "ложносекса",
  "олдово": "олдово",
  "стопхан": "стопхан",
  "пластинк": "пластинк",
  "шпажа": "шпажа",
  "деревянн": "деревянн",
  "предкоитальных": "предкоитальных",
  "оммму": "оммму",
  "накатанн": "накатанн",
  "есень": "есень",
  "ретки": "ретки",
  "некро": "некро",
  "мышом": "мышом",
  "родионовцы": "родионовцы",
  "гитаросексу": "гитаросексу",
  "алист": "алист",
  "волчится": "волчится",
  "айкидом": "айкидом",
  "кидом": "кидом",
  "коничева": "коничева",
  "чьева": "чьева",
  "складовская": "складовская",
  "кюрю": "кюрю",
  "синющие": "синющие",
  "стлива": "стлива",
  "предложь": "предложь",
  "инквизит": "инквизит",
  "прокрастинирования": "прокрастинирования",
  "небесну": "небесну",
  "приближаецца": "приближаецца",
  "балала": "балала",
  "метцентр": "метцентр",
  "перекрестке": "перекрестке",
  "даясь": "даясь",
  "включон": "включон",
  "акетпа": "акетпа",
  "ираноф": "ираноф",
  "ацилу": "ацилу",
  "йуууухууу": "йуууухууу",
  "чущее": "чущее",
  "спайдервумен": "спайдервумен",
  "голово": "голово",
  "грудьми": "грудьми",
  "насажденья": "насажденья",
  "оскор": "оскор",
  "блены": "блены",
  "рия": "рия",
  "понево": "понево",
  "витан": "витан",
  "едете?": "едете?",
  "лифте?": "лифте?",
  "ванчик": "ванчик",
  "ямщит": "ямщит",
  "веласкесу": "веласкесу",
  "уемнуться": "уемнуться",
  "заткнясь": "заткнясь",
  "шнеля": "шнеля",
  "архиидей": "архиидей",
  "лости": "лости",
  "ассоцииру": "ассоцииру",
  "ецца": "ецца",
  "эгэ": "эгэ",
  "блошарню": "блошарню",
  "переквалифициро": "переквалифициро",
  "вавши": "вавши",
  "угле-": "угле-",
  "водо-": "водо-",
  "помещается?": "помещается?",
  "кюхельбехерно": "кюхельбехерно",
  "темным": "темным",
  "самсука": "самсука",
  "хосю": "хосю",
  "возьмет": "возьмет",
  "консервированью": "консервированью",
  "послушайка": "послушайка",
  "итож": "итож",
  "ишшу": "ишшу",
  "подергался": "подергался",
  "шакиру": "шакиру",
  "шокиру": "шокиру",
  "юще": "юще",
  "бины": "бины",
  "бургунь": "бургунь",
  "самогонь": "самогонь",
  "впердоль": "впердоль",
  "ненаблюденьем": "ненаблюденьем",
  "отверт": "отверт",
  "пуанкарэ": "пуанкарэ",
  "веревки": "веревки",
  "маленьк": "маленьк",
  "ебус": "ебус",
  "долбойобов": "долбойобов",
  "водолеек": "водолеек",
  "козерожек": "козерожек",
  "овних": "овних",
  "долюбливать": "долюбливать",
  "купаш": "купаш",
  "мождя": "мождя",
  "неразнообразный": "неразнообразный",
  "сноряд": "сноряд",
  "перевелся": "перевелся",
  "гоев": "гоев",
  "сложыл": "сложыл",
  "прокрустывая": "прокрустывая",
  "децтве": "децтве",
  "свернешь": "свернешь",
  "инопланетя": "инопланетя",
  "обоже": "обоже",
  "лошар": "лошар",
  "убиииил": "убиииил",
  "заголосилось": "заголосилось",
  "обескура": "обескура",
  "сомалйського": "сомалйського",
  "прата": "прата",
  "кишен": "кишен",
  "сомал": "сомал",
  "вдома": "вдома",
  "сомалята": "сомалята",
  "шерша": "шерша",
  "шобы": "шобы",
  "баскетболистоненавистни": "баскетболистоненавистни",
  "чество": "чество",
  "льдегид": "льдегид",
  "парапара": "парапара",
  "парарара": "парарара",
  "чесслово": "чесслово",
  "ронят": "ронят",
  "изви": "изви",
  "добрю": "добрю",
  "бухтит": "бухтит",
  "туло": "туло",
  "вищо": "вищо",
  "шкою": "шкою",
  "загран": "загран",
  "ктусы": "ктусы",
  "влюблен": "влюблен",
  "анорексическом": "анорексическом",
  "питра": "питра",
  "цыкады": "цыкады",
  "стихосложенье": "стихосложенье",
  "опов": "опов",
  "набьется": "набьется",
  "клопических": "клопических",
  "хезе": "хезе",
  "наверн": "наверн",
  "кунгфей": "кунгфей",
  "селфей": "селфей",
  "Елена": "Елена",
  "Гололобова": "Гололобова",
  "бигфутов": "бигфутов",
  "возьмем": "возьмем",
  "пепперштейн": "пепперштейн",
  "два.ноль": "два.ноль",
  "настеньке": "настеньке",
  "сколковской": "сколковской",
  "тофлер": "тофлер",
  "монотавр": "монотавр",
  "помелла": "помелла",
  "прожжон": "прожжон",
  "недолюбленных": "недолюбленных",
  "экзю": "экзю",
  "перей": "перей",
  "гемо": "гемо",
  "нинград": "нинград",
  "незапихуемость": "незапихуемость",
  "съебя": "съебя",
  "шредингера": "шредингера",
  "режыссер": "режыссер",
  "травматургия": "травматургия",
  "раскровать": "раскровать",
  "гиппопотамоненавистник": "гиппопотамоненавистник",
  "гиппопотамоненавистни": "гиппопотамоненавистни",
  "полпальца": "полпальца",
  "видеонаблюде": "видеонаблюде",
  "нием": "нием",
  "тяжелым": "тяжелым",
  "айзи": "айзи",
  "гунгарун": "гунгарун",
  "герун": "герун",
  "джорждано": "джорждано",
  "бобрррята": "бобрррята",
  "обна": "обна",
  "уло": "уло",
  "обворо": "обворо",
  "убла": "убла",
  "лялист": "лялист",
  "канюч": "канюч",
  "лодца": "лодца",
  "полрогалика": "полрогалика",
  "нестрижен": "нестрижен",
  "мочи!": "мочи!",
  "чернозема": "чернозема",
  "сопогом": "сопогом",
  "аверно": "аверно",
  "аустер": "аустер",
  "уе<x_LAT>ав": "уе<x_LAT>ав",
  "ка/цы": "ка/цы",
  "перех□дим": "перех□дим",
  "зак□нн□сти": "зак□нн□сти",
  "уп□требленья": "уп□требленья",
  "мале'вич": "мале'вич",
  "еред": "еред",
  "ую": "ую",
  "ХУЯК": "ХУЯК",
  "Рефрен": "Рефрен",
  "черечур": "черечур",
  "Знакомьтесь": "Знакомьтесь",
  "Моцарт": "Моцарт",
  "Поэт": "Поэт",
  "Сольери": "Сольери",
  "Мутант": "Мутант",
  "ложииись": "ложииись",
  "Куда": "Куда",
  "Свинец": "Свинец",
  "вистни": "вистни",
  "Куко": "Куко",
  "Подлец": "Подлец",
  "Фашист": "Фашист",
  "Убийца": "Убийца",
  "Однако": "Однако",
  "Та-дам": "Та-дам",
  "сверк-сверк": "сверк-сверк",
  "Какого": "Какого",
  "Слыхать": "Слыхать",
  "крышнам": "крышнам",
  "ичезло": "ичезло",
  "водо": "водо",
  "йухууу": "йухууу"
}